best/__init__.py
best/integration/__init__.py
best/unit/__init__.py
best/unit/conftest.py
best/unit/test_glue_session.py
best/unit/test_glue_session_demo.py
best/unit/test_session_apis.py
pixman-0.7.6.dist-info/LICENSE.txt
pixman-0.7.6.dist-info/METADATA
pixman-0.7.6.dist-info/WHEEL
pixman-0.7.6.dist-info/top_level.txt
pixman-0.7.6.dist-info/RECORD
